README.md
pyproject.toml
setup.py
src/GridsAndHexes.egg-info/PKG-INFO
src/GridsAndHexes.egg-info/SOURCES.txt
src/GridsAndHexes.egg-info/dependency_links.txt
src/GridsAndHexes.egg-info/top_level.txt
src/gridsandhexes/__init__.py
src/gridsandhexes/__main__.py